pyseis/__init__.py
pyseis/signal.py
pyseis/download/__init__.py
pyseis/plot/__init__.py
pyseis/plot/plot_util.py
pyseis/utils/__init__.py
pyseis/utils/io.py
pyseis/utils/source.py
pyseis-0.0.1.dist-info/METADATA
pyseis-0.0.1.dist-info/WHEEL
pyseis-0.0.1.dist-info/top_level.txt
pyseis-0.0.1.dist-info/RECORD
